easycheck/__init__.py
easycheck/easycheck.py
easycheck-0.12.1.dist-info/LICENSE
easycheck-0.12.1.dist-info/METADATA
easycheck-0.12.1.dist-info/WHEEL
easycheck-0.12.1.dist-info/top_level.txt
easycheck-0.12.1.dist-info/RECORD
