Metadata-Version: 2.2
Name: easycheck
Version: 0.12.1
Summary: A tool for checking conditions in Python
Author: KeBoan, Darsoo, Karollayna
Author-email: Nyggus <nyggus@gmail.com>
License: MIT License
Project-URL: Homepage, https://github.com/nyggus/easycheck/
Classifier: Intended Audience :: Developers
Classifier: Programming Language :: Python :: 3
Classifier: Programming Language :: Python :: 3.8
Classifier: Programming Language :: Python :: 3.9
Classifier: Programming Language :: Python :: 3.10
Classifier: Programming Language :: Python :: 3.11
Classifier: Programming Language :: Python :: 3.12
Classifier: License :: OSI Approved :: MIT License
Classifier: Operating System :: OS Independent
Classifier: Topic :: Software Development :: Libraries :: Python Modules
Requires-Python: >=3.8
License-File: LICENSE
Provides-Extra: dev
Requires-Dist: wheel; extra == "dev"
Requires-Dist: black; extra == "dev"
Requires-Dist: pytest; extra == "dev"
Requires-Dist: mypy; extra == "dev"
Requires-Dist: setuptools; extra == "dev"
Requires-Dist: build; extra == "dev"
